invenio_vocabularies/__init__.py
invenio_vocabularies/cli.py
invenio_vocabularies/config.py
invenio_vocabularies/ext.py
invenio_vocabularies/factories.py
invenio_vocabularies/fixtures.py
invenio_vocabularies/jobs.py
invenio_vocabularies/proxies.py
invenio_vocabularies/views.py
invenio_vocabularies/webpack.py
invenio_vocabularies/administration/__init__.py
invenio_vocabularies/administration/views/__init__.py
invenio_vocabularies/administration/views/vocabularies.py
invenio_vocabularies/alembic/17c703ce1eb7_create_names_table.py
invenio_vocabularies/alembic/3ba812d80559_add_internal_name_id.py
invenio_vocabularies/alembic/4a9a4fd235f8_create_vocabulary_schemes.py
invenio_vocabularies/alembic/4f365fced43f_create_vocabularies_tables.py
invenio_vocabularies/alembic/55a700f897b6_add_names_and_afiliations_pid_column.py
invenio_vocabularies/alembic/6312f33645c1_create_affiliations_table.py
invenio_vocabularies/alembic/676dd587542d_create_funders_vocabulary_table.py
invenio_vocabularies/alembic/8ff82dfb0be8_create_vocabularies_branch.py
invenio_vocabularies/alembic/__init__.py
invenio_vocabularies/alembic/af2457652217_drop_unique_constraint_from_internal_id.py
invenio_vocabularies/alembic/d00af88aac94_change_datetime_types.py
invenio_vocabularies/alembic/e1146238edd3_create_awards_table.py
invenio_vocabularies/assets/semantic-ui/js/invenio_vocabularies/.eslintrc.yml
invenio_vocabularies/assets/semantic-ui/js/invenio_vocabularies/.prettierrc
invenio_vocabularies/assets/semantic-ui/js/invenio_vocabularies/index.js
invenio_vocabularies/assets/semantic-ui/js/invenio_vocabularies/package.json
invenio_vocabularies/assets/semantic-ui/js/invenio_vocabularies/src/index.js
invenio_vocabularies/assets/semantic-ui/js/invenio_vocabularies/src/contrib/index.js
invenio_vocabularies/assets/semantic-ui/js/invenio_vocabularies/src/contrib/forms/index.js
invenio_vocabularies/assets/semantic-ui/js/invenio_vocabularies/src/contrib/forms/Funding/AwardResults.js
invenio_vocabularies-10.0.0.dist-info/licenses/AUTHORS.rst
invenio_vocabularies-10.0.0.dist-info/licenses/LICENSE
invenio_vocabularies-10.0.0.dist-info/METADATA
invenio_vocabularies-10.0.0.dist-info/WHEEL
invenio_vocabularies-10.0.0.dist-info/entry_points.txt
invenio_vocabularies-10.0.0.dist-info/top_level.txt
invenio_vocabularies-10.0.0.dist-info/RECORD
