Metadata-Version: 2.4
Name: invenio-vocabularies
Version: 10.0.0
Summary: Invenio module for managing vocabularies.
Home-page: https://github.com/inveniosoftware/invenio-vocabularies
Author: CERN
Author-email: info@inveniosoftware.org
License: MIT
Keywords: invenio vocabulary management
Platform: any
Classifier: Development Status :: 5 - Production/Stable
Requires-Python: >=3.7
License-File: LICENSE
License-File: AUTHORS.rst
Requires-Dist: invenio-i18n<4.0.0,>=3.0.0
Requires-Dist: invenio-records-resources<10.0.0,>=9.0.0
Requires-Dist: invenio-administration<6.0.0,>=5.0.0
Requires-Dist: invenio-jobs<8.0.0,>=7.0.0
Requires-Dist: lxml>=4.5.0
Requires-Dist: pycountry>=24.0.0
Requires-Dist: PyYAML>=5.4.1
Requires-Dist: regex>=2024.7.24
Requires-Dist: SPARQLWrapper>=2.0.0
Provides-Extra: s3fs
Requires-Dist: s3fs>=2024.6.1; extra == "s3fs"
Provides-Extra: oaipmh
Requires-Dist: invenio-oaipmh-scythe>=0.13.0; extra == "oaipmh"
Provides-Extra: rdf
Requires-Dist: rdflib>=7.0.0; extra == "rdf"
Provides-Extra: sparql
Requires-Dist: SPARQLWrapper>=2.0.0; extra == "sparql"
Provides-Extra: tests
Requires-Dist: pytest-black>=0.6.0; extra == "tests"
Requires-Dist: invenio-app<4.0.0,>=3.0.0; extra == "tests"
Requires-Dist: invenio-db[mysql,postgresql]<3.0.0,>=2.2.0; extra == "tests"
Requires-Dist: pytest_httpserver>=1.0.10; extra == "tests"
Requires-Dist: pytest-invenio<5.0.0,>=4.0.0; extra == "tests"
Requires-Dist: Sphinx>=4.5; extra == "tests"
Provides-Extra: elasticsearch7
Requires-Dist: invenio-search[elasticsearch7]<4.0.0,>=3.0.0; extra == "elasticsearch7"
Provides-Extra: opensearch1
Requires-Dist: invenio-search[opensearch1]<4.0.0,>=3.0.0; extra == "opensearch1"
Provides-Extra: opensearch2
Requires-Dist: invenio-search[opensearch2]<4.0.0,>=3.0.0; extra == "opensearch2"
Provides-Extra: mysql
Provides-Extra: postgresql
Provides-Extra: sqlite
Dynamic: license-file
